{
  "pricingpage_BusinessUnit": " North ",
  "pricingpage_Revenue": "$43,688",
  "pricingpage_SVA": "$7,836",
  "pricingpage_ROE": "17.57%",
  "RevenueWithDeal": "$114,238",
  "RevenueImpact": "$70,550",
  "pricingpage_ROEWithDeal": "19.80%",
  "pricingpage_ROEImpact": "2.24%",
  "pricingpage_productIndustryCode": " 9900 Individuals ",
  "pricingpage_limit": "$1,000,000",
  "pricingpageforecast_Margin": "$47,550",
  "pricingpageforecast_Fees": "$27,500",
  "pricingpageforecast_Revenue": "$70,550",
  "pricingpageforecast_Capital Benefit": "$2,543",
  "pricingpageforecast_Expected Loss": "$13,840",
  "pricingpageforecast_Brokerage": " - ",
  "pricingpageforecast_Trail": " - ",
  "pricingpageforecast_Opex": "$1,500",
  "pricingpageforecast_NPBT": "$57,752",
  "pricingpageforecast_Tax": "$17,326",
  "pricingpageforecast_Franking Credit": "$12,128",
  "pricingpageforecast_NPAT": "$52,555",
  "pricingpageforecast_Capital Charge": "$23,518",
  "pricingpageforecast_SVA": "$29,036",
  "pricingpageforecast_ROE": "20.67%",
  "pricingpageforecast_NPM": "74.49%",
  "pricingpage_Exposure": "$1,000,000",
  "pricingpage_State": " Queensland "
}